README.md
setup.cfg
setup.py
speech2text_client/__init__.py
speech2text_client/client.py
speech2text_client/enums.py
speech2text_client/options.py
speech2text_client/recognitions.py
speech2text_client/task.py
speech2text_client/user.py
speech2text_client.egg-info/PKG-INFO
speech2text_client.egg-info/SOURCES.txt
speech2text_client.egg-info/dependency_links.txt
speech2text_client.egg-info/requires.txt
speech2text_client.egg-info/top_level.txt