Metadata-Version: 2.1
Name: speech2text-client
Version: 0.1.4
Summary: Python SDK for speech2text.ru
Home-page: https://speech2text.ru/
Author: Dmitry Belov
Author-email: info@speech2text.ru
License: UNKNOWN
Project-URL: Documentation, https://github.com/Speech2TextR/s2t-client-python
Keywords: speech2text s2t распознание
Platform: UNKNOWN
Classifier: Programming Language :: Python :: 3.11
Classifier: License :: OSI Approved :: MIT License
Classifier: Operating System :: OS Independent
Requires-Python: >=3.7
